flask_jerify
